sqlo2/__init__.py
sqlo2/sqlo2.cpython-38-darwin.so
sqlo2-0.25.0.dist-info/LICENSE
sqlo2-0.25.0.dist-info/METADATA
sqlo2-0.25.0.dist-info/WHEEL
sqlo2-0.25.0.dist-info/top_level.txt
sqlo2-0.25.0.dist-info/RECORD
