Metadata-Version: 2.1
Name: sqlo2
Version: 0.25.0
Summary: Python bindings for sqlparser-rs
Home-page: https://github.com/joocer/sqloxide
Author: Justin Joyce
Author-email: justin.joyce@joocer.com
Requires-Python: >=3.6.0,<4.0
License-File: LICENSE
